pyodhean/__init__.py
pyodhean/defaults.py
pyodhean/interface.py
pyodhean/model.py
pyodhean/utils.py
pyodhean-1.0.0.dist-info/LICENSE
pyodhean-1.0.0.dist-info/METADATA
pyodhean-1.0.0.dist-info/WHEEL
pyodhean-1.0.0.dist-info/top_level.txt
pyodhean-1.0.0.dist-info/RECORD
